python_abc/__init__.py
python_abc/__main__.py
python_abc/calculate.py
python_abc/vector.py
python_abc-0.1.0.dist-info/METADATA
python_abc-0.1.0.dist-info/WHEEL
python_abc-0.1.0.dist-info/entry_points.txt
python_abc-0.1.0.dist-info/top_level.txt
python_abc-0.1.0.dist-info/RECORD
