Metadata-Version: 2.1
Name: python-abc
Version: 0.1.0
Summary: A python implementation of the ABC Sofware metric
Home-page: https://github.com/eoinnoble/python-abc
Author: Eoin Noble
Author-email: eoin@eoinnoble.com
License: UNKNOWN
Platform: UNKNOWN
Classifier: License :: Freely Distributable
Classifier: Programming Language :: Python :: 3.9
Classifier: Typing :: Typed
